<?xml version="1.0"?>
<all>
  <!-- This parameter patch file updates the parameter file with the necessary changes -->
  <!-- for PR  1093. This PR updates the allometry parameters for the default global PFTs -->


  <!-- General xml file usage notes: -->
  <!-- Special mod types "variable_add": creates a new variable
		 "dimension_add": creates a new dimension
		 "variable_del": removes a variable, must include attribute "name" 
		 "variable_change": change values in the parameter, possibly including the name, and
                          this must also come with a name attribute as well -->
  <!-- To change a dimension. The easiest way to script this, is to delete the variables
		 that use it, delete the dimension. Re-add it with the new size, and then re-add
		 the variables -->
  <!-- -->
  
  <base_file>archive/api28.0.0_103023_fates_params_default.cdl </base_file>
  <new_file>fates_params_default.cdl</new_file>
  <pft_list> 1,2,3,4,5,6,7,8,9,10,11,12 </pft_list>
  <mods>
    <mod type="variable_change" name="fates_allom_agb1">
      <di>  fates_pft </di>
      <!--old vals
            0.06896,0.06896,   0.06896,   0.06896,   0.06896,0.06896,   0.06896, 0.06896, 0.06896, 0.01, 0.01, 0.01  -->
      <val> 0.0673, 0.1364012, 0.0393057, 0.2653695, 0.0673, 0.0728698, 0.06896, 0.06896, 0.06896, 0.01, 0.01, 0.01   </val>
    </mod>
    <mod type="variable_change" name="fates_allom_agb2">
      <di>  fates_pft </di>
      <!--old vals
            0.572, 0.572,     0.572,    0.572,     0.572, 0.572,     0.572, 0.572, 0.572, 0.572, 0.572, 0.572 -->
      <val> 0.976, 0.9449041, 1.087335, 0.8321321, 0.976, 1.0373211, 0.572, 0.572, 0.572, 0.572, 0.572, 0.572   </val>
    </mod>
    <mod type="variable_change" name="fates_allom_amode">
      <di>  fates_pft </di>
      <!--old vals
            1, 1, 1, 1, 1, 1, 1, 1, 1, 1, 1, 1 -->
      <val> 3, 3, 3, 3, 3, 3, 1, 1, 1, 1, 1, 1 </val>
    </mod>
    <mod type="variable_change" name="fates_allom_d2bl1">
      <di>  fates_pft </di>
      <!--old vals
            0.07, 0.07, 0.07, 0.07, 0.07, 0.07, 0.07, 0.07, 0.07, 0.07, 0.07, 0.07 -->
      <val> 0.04, 0.07, 0.07, 0.01, 0.04, 0.07, 0.07, 0.07, 0.07, 0.07, 0.07, 0.07 </val>
    </mod>
    <mod type="variable_change" name="fates_allom_d2bl2">
      <di>  fates_pft </di>
      <!--old vals
            1.3,       1.3,       1.3,       1.3,       1.3,       1.3,       1.3, 1.3, 1.3, 1.3, 1.3, 1.3 -->
      <val> 1.6019679, 1.5234373, 1.3051237, 1.9621397, 1.6019679, 1.3998939, 1.3, 1.3, 1.3, 1.3, 1.3, 1.3 </val>
    </mod>
    <mod type="variable_change" name="fates_allom_lmode">
      <di>  fates_pft </di>
      <!--old vals
            1, 1, 1, 1, 1, 1, 1, 1, 1, 1, 1, 1 -->
      <val> 2, 2, 2, 2, 2, 2, 1, 1, 1, 1, 1, 1 </val>
    </mod>
    <mod type="variable_change" name="fates_allom_blca_expnt_diff">
      <di>  fates_pft </di>
      <!--old vals
             0,     0,     0,     0,     0,     0,    0, 0, 0, 0, 0, 0 -->
      <val> -0.12, -0.34, -0.32, -0.22, -0.12, -0.35, 0, 0, 0, 0, 0, 0  </val>
    </mod>
    <mod type="variable_change" name="fates_allom_d2ca_coefficient_max">
      <di>  fates_pft </di>
      <!--old vals
            0.6568464, 0.6568464, 0.6568464, 0.6568464, 0.6568464, 0.6568464, 0.6568464, 0.6568464, 0.6568464, 0.6568464, 0.6568464, 0.6568464 -->
      <val> 0.2715891, 0.3693718, 1.0787259, 0.0579297, 0.2715891, 1.1553612, 0.6568464, 0.6568464, 0.6568464, 0.6568464, 0.6568464, 0.6568464  </val>
    </mod>
    <mod type="variable_change" name="fates_allom_d2ca_coefficient_min">
      <di>  fates_pft </di>
      <!--old vals
            0.3381119, 0.3381119, 0.3381119, 0.3381119, 0.3381119, 0.3381119, 0.3381119, 0.3381119, 0.3381119, 0.3381119, 0.3381119, 0.3381119 -->
      <val> 0.2715891, 0.3693718, 1.0787259, 0.0579297, 0.2715891, 1.1553612, 0.6568464, 0.6568464, 0.6568464, 0.6568464, 0.6568464, 0.6568464  </val>
    </mod>
    <mod type="variable_change" name="fates_allom_d2h1">
      <di>  fates_pft </di>
      <!--old vals
            0.64,        0.64,       0.64,        0.64,        0.64,      0.64,       0.64, 0.64, 0.64, 0.64, 0.64, 0.64   -->
      <val> 78.4087704, 306.842667, 106.8745821, 104.3586841, 78.4087704, 31.4557047, 0.64, 0.64, 0.64, 0.64, 0.64, 0.64  </val>
    </mod>
    <mod type="variable_change" name="fates_allom_d2h2">
      <di>  fates_pft </di>
      <!--old vals
            0.37,       0.37,       0.37,       0.37,       0.37,      0.37, 0.37, 0.37, 0.37, 0.37, 0.37, 0.37-->
      <val> 0.8124383, 0.752377, 0.9471302, 1.1146973, 0.8124383, 0.9734088, 0.37, 0.37, 0.37, 0.37, 0.37, 0.37 </val>
    </mod>
    <mod type="variable_change" name="fates_allom_d2h3">
      <di>  fates_pft </di>
      <!--old vals 
            -999.9,      -999.9,     -999.9,       -999.9,      -999.9,      -999.9,  -999.9, -999.9, -999.9, -999.9, -999.9, -999.9 -->
      <val> 47.6666164, 196.6865691, 93.9790461, 160.6835089, 47.6666164, 16.5928174, -999.9, -999.9, -999.9, -999.9, -999.9, -999.9  </val>
    </mod>
    <mod type="variable_change" name="fates_allom_dbh_maxheight">
      <di>  fates_pft </di>
      <!--old vals
            90,   80,   80,   80,   90,   80,   3, 3, 2, 0.35, 0.35, 0.35   -->
      <val> 1000, 1000, 1000, 1000, 1000, 1000, 3, 3, 2, 0.35, 0.35, 0.35  </val>
    </mod>
    <mod type="variable_change" name="fates_allom_hmode">
      <di>  fates_pft </di>
      <!--old vals
            1, 1, 1, 1, 1, 1, 1, 1, 1, 1, 1, 1 -->
      <val> 5, 5, 5, 5, 5, 5, 1, 1, 1, 1, 1, 1  </val>
    </mod>
    <mod type="variable_change" name="fates_wood_density">
      <di>  fates_pft </di>
      <!--old vals
            0.7,      0.4,      0.7,      0.53,     0.7,      0.7,      0.7, 0.7, 0.7, 0.7, 0.7, 0.7-->
      <val> 0.548327, 0.442350, 0.454845, 0.754336, 0.548327, 0.566452, 0.7, 0.7, 0.7, 0.7, 0.7, 0.7  </val>
    </mod>
  </mods>
</all>
